infodb/__init__.py
infodb/__main__.py
infodb/db.py
infodb/util.py
infodb-0.0.2.dist-info/METADATA
infodb-0.0.2.dist-info/WHEEL
infodb-0.0.2.dist-info/top_level.txt
infodb-0.0.2.dist-info/RECORD
